monetdb_stethoscope/__init__.py
monetdb_stethoscope/api.py
monetdb_stethoscope/connection/__init__.py
monetdb_stethoscope/connection/api.py
monetdb_stethoscope/filtering.py
monetdb_stethoscope/formatting.py
monetdb_stethoscope/parsing.py
monetdb_stethoscope/stethoscope.py
monetdb_stethoscope/transformers.py
monetdb_stethoscope/utilities.py
monetdb_stethoscope-0.5.0.dist-info/LICENSE
monetdb_stethoscope-0.5.0.dist-info/METADATA
monetdb_stethoscope-0.5.0.dist-info/WHEEL
monetdb_stethoscope-0.5.0.dist-info/entry_points.txt
monetdb_stethoscope-0.5.0.dist-info/RECORD
