Metadata-Version: 2.1
Name: monetdb_stethoscope
Version: 0.5.0
Summary: MonetDB profiler connection tool
Home-page: https://github.com/MonetDBSolutions/monetdb-stethoscope
Author: Panagiotis Koutsourakis
Author-email: kutsurak@monetdbsolutions.com
Requires-Python: >=3.7,<4.0
Classifier: Programming Language :: Python :: 3
Classifier: Programming Language :: Python :: 3.7
Classifier: Programming Language :: Python :: 3.8
Classifier: Programming Language :: Python :: 3.9
Classifier: Programming Language :: Python :: 3.10
Classifier: Programming Language :: Python :: 3.11
Classifier: Programming Language :: Python :: 3.12
Requires-Dist: pymonetdb (>=1.6.2,<2.0.0)
Project-URL: Repository, https://github.com/MonetDBSolutions/monetdb-stethoscope
